aws_dynamodb_parallel_scan/__init__.py
aws_dynamodb_parallel_scan/py.typed
aws_dynamodb_parallel_scan-1.2.0.dist-info/WHEEL
aws_dynamodb_parallel_scan-1.2.0.dist-info/entry_points.txt
aws_dynamodb_parallel_scan-1.2.0.dist-info/METADATA
aws_dynamodb_parallel_scan-1.2.0.dist-info/RECORD
