Metadata-Version: 2.3
Name: aws-dynamodb-parallel-scan
Version: 1.2.0
Summary: Amazon DynamoDB Parallel Scan Paginator for boto3.
Author: Sami Jaktholm
Author-email: Sami Jaktholm <sjakthol@outlook.com>
Requires-Dist: boto3
Requires-Python: >=3.10
